_hellchin/__init__.py
_hellchin/logger.py
_hellchin/assertion/__init__.py
_hellchin/assertion/base_soft_assert.py
_hellchin/assertion/logger.py
_hellchin/assertion/method_assert.py
_hellchin/assertion/postman.py
hellchin/__init__.py
hellchin-0.0.1.dist-info/licenses/LICENSE
tests/__init__.py
tests/test_soft_assert/__init__.py
tests/test_soft_assert/test_demo.py
tests/test_soft_assert/test_method_assert.py
tests/test_soft_assert/test_soft_assert.py
hellchin-0.0.1.dist-info/METADATA
hellchin-0.0.1.dist-info/WHEEL
hellchin-0.0.1.dist-info/top_level.txt
hellchin-0.0.1.dist-info/RECORD
