Metadata-Version: 2.4
Name: hellchin
Version: 0.0.1
Summary: 一个属于软件测试工程师使用的工具库.
Author: hellchin
Author-email: zhuangyuqiu986@163.com
Classifier: Programming Language :: Python :: 3
Classifier: License :: OSI Approved :: MIT License
Classifier: Operating System :: OS Independent
License-File: LICENSE
Requires-Dist: pytest>=6.0.0
Dynamic: author
Dynamic: author-email
Dynamic: classifier
Dynamic: description
Dynamic: description-content-type
Dynamic: license-file
Dynamic: requires-dist
Dynamic: summary
